pascal_voc_tools/__init__.py
pascal_voc_tools/_pad_data.py
pascal_voc_tools/anchors_kmeans.py
pascal_voc_tools/annotations_tools.py
pascal_voc_tools/aspect_ratios.py
pascal_voc_tools/darknet_config.py
pascal_voc_tools/false_positive_argument.py
pascal_voc_tools/image_tools.py
pascal_voc_tools/jpegimages_tools.py
pascal_voc_tools/tools.py
pascal_voc_tools/voc_tools.py
pascal_voc_tools/xml_tools.py
pascal_voc_tools/Augmenter/__init__.py
pascal_voc_tools/Augmenter/bbox_util.py
pascal_voc_tools/Augmenter/data_aug.py
pascal_voc_tools/Evaluater/__init__.py
pascal_voc_tools/Evaluater/tools.py
pascal_voc_tools/utils/__init__.py
pascal_voc_tools/utils/nms.py
pascal_voc_tools-0.2.3.dist-info/LICENSE
pascal_voc_tools-0.2.3.dist-info/METADATA
pascal_voc_tools-0.2.3.dist-info/WHEEL
pascal_voc_tools-0.2.3.dist-info/pbr.json
pascal_voc_tools-0.2.3.dist-info/top_level.txt
pascal_voc_tools-0.2.3.dist-info/RECORD
