Metadata-Version: 2.1
Name: pascal-voc-tools
Version: 0.2.3
Summary: Some PascalVOC dataset tools
Home-page: https://github.com/wang-tf/pascal_voc_tools
Author: ternence wang
Author-email: ternencewang2015@outlook.com
License: MIT
Platform: UNKNOWN
Classifier: Intended Audience :: Developers
Classifier: Intended Audience :: Information Technology
Classifier: License :: OSI Approved :: MIT License
Classifier: Operating System :: OS Independent
Classifier: Programming Language :: Python
Requires-Dist: lxml
Requires-Dist: opencv-python
Requires-Dist: tqdm
Requires-Dist: matplotlib
Requires-Dist: sphinxcontrib-apidoc
